[
  {
    "name": "Trafyx",
    "url": "https://trafyx.kyrexi.tech",
    "owner": "prnvtripathi",
    "status": "UP",
    "code": 200,
    "error": null,
    "rtt": 295,
    "checkedAt": "2025-10-10T19:26:51.595Z"
  },
  {
    "name": "Monkeys",
    "url": "https://monkeys.com.co",
    "owner": "prnvtripathi",
    "status": "UP",
    "code": 200,
    "error": null,
    "rtt": 128,
    "checkedAt": "2025-10-10T19:26:51.723Z"
  },
  {
    "name": "Obligence",
    "url": "https://obligence.kyrexi.tech",
    "owner": "prnvtripathi",
    "status": "UP",
    "code": 200,
    "error": null,
    "rtt": 1836,
    "checkedAt": "2025-10-10T19:26:53.559Z"
  }
]