[
  {
    "name": "Trafyx",
    "url": "https://trafyx.kyrexi.tech",
    "owner": "prnvtripathi",
    "status": "UP",
    "code": 200,
    "error": null,
    "rtt": 7556,
    "checkedAt": "2025-10-30T23:10:21.247Z"
  },
  {
    "name": "Monkeys",
    "url": "https://monkeys.com.co",
    "owner": "prnvtripathi",
    "status": "UP",
    "code": 200,
    "error": null,
    "rtt": 102,
    "checkedAt": "2025-10-30T23:10:21.350Z"
  },
  {
    "name": "Obligence",
    "url": "https://obligence.kyrexi.tech",
    "owner": "prnvtripathi",
    "status": "UP",
    "code": 200,
    "error": null,
    "rtt": 1430,
    "checkedAt": "2025-10-30T23:10:22.780Z"
  }
]