[
  {
    "name": "Trafyx",
    "url": "https://trafyx.kyrexi.tech",
    "owner": "prnvtripathi",
    "status": "UP",
    "code": 200,
    "error": null,
    "rtt": 7060,
    "checkedAt": "2025-11-02T22:36:51.439Z"
  },
  {
    "name": "Monkeys",
    "url": "https://monkeys.com.co",
    "owner": "prnvtripathi",
    "status": "UP",
    "code": 200,
    "error": null,
    "rtt": 235,
    "checkedAt": "2025-11-02T22:36:51.674Z"
  },
  {
    "name": "Obligence",
    "url": "https://obligence.kyrexi.tech",
    "owner": "prnvtripathi",
    "status": "UP",
    "code": 200,
    "error": null,
    "rtt": 1526,
    "checkedAt": "2025-11-02T22:36:53.200Z"
  }
]