[
  {
    "name": "Trafyx",
    "url": "https://trafyx.kyrexi.tech",
    "owner": "prnvtripathi",
    "status": "UP",
    "code": 200,
    "error": null,
    "rtt": 4226,
    "checkedAt": "2025-10-08T04:39:04.758Z"
  },
  {
    "name": "Monkeys",
    "url": "https://monkeys.com.co",
    "owner": "prnvtripathi",
    "status": "UP",
    "code": 200,
    "error": null,
    "rtt": 126,
    "checkedAt": "2025-10-08T04:39:04.884Z"
  },
  {
    "name": "Obligence",
    "url": "https://obligence.kyrexi.tech",
    "owner": "prnvtripathi",
    "status": "UP",
    "code": 200,
    "error": null,
    "rtt": 1645,
    "checkedAt": "2025-10-08T04:39:06.529Z"
  }
]