[
  {
    "name": "Trafyx",
    "url": "https://trafyx.kyrexi.tech",
    "owner": "prnvtripathi",
    "status": "UP",
    "code": 200,
    "error": null,
    "rtt": 7015,
    "checkedAt": "2025-11-01T14:25:22.709Z"
  },
  {
    "name": "Monkeys",
    "url": "https://monkeys.com.co",
    "owner": "prnvtripathi",
    "status": "UP",
    "code": 200,
    "error": null,
    "rtt": 374,
    "checkedAt": "2025-11-01T14:25:23.084Z"
  },
  {
    "name": "Obligence",
    "url": "https://obligence.kyrexi.tech",
    "owner": "prnvtripathi",
    "status": "UP",
    "code": 200,
    "error": null,
    "rtt": 1842,
    "checkedAt": "2025-11-01T14:25:24.926Z"
  }
]