[
  {
    "name": "Trafyx",
    "url": "https://trafyx.kyrexi.tech",
    "owner": "prnvtripathi",
    "status": "UP",
    "code": 200,
    "error": null,
    "rtt": 269,
    "checkedAt": "2025-11-20T06:57:47.377Z"
  },
  {
    "name": "Monkeys Production",
    "url": "https://monkeys.support/healthz",
    "owner": "prnvtripathi",
    "status": "UP",
    "code": 200,
    "error": null,
    "rtt": 978,
    "checkedAt": "2025-11-20T06:57:48.363Z"
  },
  {
    "name": "Monkeys Development",
    "url": "https://dev.monkeys.support/healthz",
    "owner": "prnvtripathi",
    "status": "UP",
    "code": 200,
    "error": null,
    "rtt": 1005,
    "checkedAt": "2025-11-20T06:57:49.370Z"
  },
  {
    "name": "Obligence",
    "url": "https://obligence.kyrexi.tech",
    "owner": "prnvtripathi",
    "status": "UP",
    "code": 200,
    "error": null,
    "rtt": 1507,
    "checkedAt": "2025-11-20T06:57:50.879Z"
  }
]