[
  {
    "name": "Trafyx",
    "url": "https://trafyx.kyrexi.tech",
    "owner": "prnvtripathi",
    "status": "UP",
    "code": 200,
    "error": null,
    "rtt": 6189,
    "checkedAt": "2025-12-13T22:31:52.233Z"
  },
  {
    "name": "Monkeys Production",
    "url": "https://monkeys.support/healthz",
    "owner": "prnvtripathi",
    "status": "UP",
    "code": 200,
    "error": null,
    "rtt": 768,
    "checkedAt": "2025-12-13T22:31:53.009Z"
  },
  {
    "name": "Monkeys Development",
    "url": "https://dev.monkeys.support/healthz",
    "owner": "prnvtripathi",
    "status": "UP",
    "code": 200,
    "error": null,
    "rtt": 706,
    "checkedAt": "2025-12-13T22:31:53.718Z"
  },
  {
    "name": "Obligence",
    "url": "https://obligence.kyrexi.tech",
    "owner": "prnvtripathi",
    "status": "UP",
    "code": 200,
    "error": null,
    "rtt": 1717,
    "checkedAt": "2025-12-13T22:31:55.437Z"
  }
]