[
  {
    "name": "Trafyx",
    "url": "https://trafyx.kyrexi.tech",
    "owner": "prnvtripathi",
    "status": "DOWN",
    "code": 0,
    "error": "fetch failed",
    "rtt": 0,
    "checkedAt": "2026-02-17T08:07:06.307Z"
  },
  {
    "name": "Monkeys Production",
    "url": "https://monkeys.support/healthz",
    "owner": "prnvtripathi",
    "status": "UP",
    "code": 200,
    "error": null,
    "rtt": 753,
    "checkedAt": "2026-02-17T08:07:07.394Z"
  },
  {
    "name": "Monkeys Development",
    "url": "https://dev.monkeys.support/healthz",
    "owner": "prnvtripathi",
    "status": "UP",
    "code": 200,
    "error": null,
    "rtt": 792,
    "checkedAt": "2026-02-17T08:07:08.189Z"
  },
  {
    "name": "Obligence",
    "url": "https://obligence.kyrexi.tech",
    "owner": "prnvtripathi",
    "status": "DOWN",
    "code": 0,
    "error": "fetch failed",
    "rtt": 0,
    "checkedAt": "2026-02-17T08:07:08.222Z"
  }
]