[
  {
    "name": "Trafyx",
    "url": "https://trafyx.kyrexi.tech",
    "owner": "prnvtripathi",
    "status": "DOWN",
    "code": 0,
    "error": "fetch failed",
    "rtt": 0,
    "checkedAt": "2026-02-10T13:46:32.370Z"
  },
  {
    "name": "Monkeys Production",
    "url": "https://monkeys.support/healthz",
    "owner": "prnvtripathi",
    "status": "UP",
    "code": 200,
    "error": null,
    "rtt": 859,
    "checkedAt": "2026-02-10T13:46:33.561Z"
  },
  {
    "name": "Monkeys Development",
    "url": "https://dev.monkeys.support/healthz",
    "owner": "prnvtripathi",
    "status": "DOWN",
    "code": 502,
    "error": null,
    "rtt": 4190,
    "checkedAt": "2026-02-10T13:46:37.753Z"
  },
  {
    "name": "Obligence",
    "url": "https://obligence.kyrexi.tech",
    "owner": "prnvtripathi",
    "status": "DOWN",
    "code": 0,
    "error": "fetch failed",
    "rtt": 0,
    "checkedAt": "2026-02-10T13:46:38.118Z"
  }
]