[
  {
    "name": "Trafyx",
    "url": "https://trafyx.kyrexi.tech",
    "owner": "prnvtripathi",
    "status": "DOWN",
    "code": 0,
    "error": "fetch failed",
    "rtt": 0,
    "checkedAt": "2026-04-17T23:08:21.184Z"
  },
  {
    "name": "Monkeys Production",
    "url": "https://monkeys.support/healthz",
    "owner": "prnvtripathi",
    "status": "UP",
    "code": 200,
    "error": null,
    "rtt": 897,
    "checkedAt": "2026-04-17T23:08:22.319Z"
  },
  {
    "name": "Monkeys Development",
    "url": "https://dev.monkeys.support/healthz",
    "owner": "prnvtripathi",
    "status": "UP",
    "code": 200,
    "error": null,
    "rtt": 949,
    "checkedAt": "2026-04-17T23:08:23.270Z"
  },
  {
    "name": "Obligence",
    "url": "https://obligence.kyrexi.tech",
    "owner": "prnvtripathi",
    "status": "DOWN",
    "code": 0,
    "error": "fetch failed",
    "rtt": 0,
    "checkedAt": "2026-04-17T23:08:23.336Z"
  }
]