[
  {
    "name": "Trafyx",
    "url": "https://trafyx.kyrexi.tech",
    "owner": "prnvtripathi",
    "status": "UP",
    "code": 200,
    "error": null,
    "rtt": 6179,
    "checkedAt": "2025-12-29T15:34:33.647Z"
  },
  {
    "name": "Monkeys Production",
    "url": "https://monkeys.support/healthz",
    "owner": "prnvtripathi",
    "status": "UP",
    "code": 200,
    "error": null,
    "rtt": 904,
    "checkedAt": "2025-12-29T15:34:34.560Z"
  },
  {
    "name": "Monkeys Development",
    "url": "https://dev.monkeys.support/healthz",
    "owner": "prnvtripathi",
    "status": "DOWN",
    "code": 502,
    "error": null,
    "rtt": 3972,
    "checkedAt": "2025-12-29T15:34:38.535Z"
  },
  {
    "name": "Obligence",
    "url": "https://obligence.kyrexi.tech",
    "owner": "prnvtripathi",
    "status": "UP",
    "code": 200,
    "error": null,
    "rtt": 1649,
    "checkedAt": "2025-12-29T15:34:40.551Z"
  }
]