[
  {
    "name": "Trafyx",
    "url": "https://trafyx.kyrexi.tech",
    "owner": "prnvtripathi",
    "status": "DOWN",
    "code": 0,
    "error": "fetch failed",
    "rtt": 0,
    "checkedAt": "2026-02-07T19:38:03.472Z"
  },
  {
    "name": "Monkeys Production",
    "url": "https://monkeys.support/healthz",
    "owner": "prnvtripathi",
    "status": "UP",
    "code": 200,
    "error": null,
    "rtt": 919,
    "checkedAt": "2026-02-07T19:38:04.803Z"
  },
  {
    "name": "Monkeys Development",
    "url": "https://dev.monkeys.support/healthz",
    "owner": "prnvtripathi",
    "status": "DOWN",
    "code": 502,
    "error": null,
    "rtt": 3823,
    "checkedAt": "2026-02-07T19:38:08.628Z"
  },
  {
    "name": "Obligence",
    "url": "https://obligence.kyrexi.tech",
    "owner": "prnvtripathi",
    "status": "DOWN",
    "code": 0,
    "error": "fetch failed",
    "rtt": 0,
    "checkedAt": "2026-02-07T19:38:09.039Z"
  }
]