[
  {
    "name": "Trafyx",
    "url": "https://trafyx.kyrexi.tech",
    "owner": "prnvtripathi",
    "status": "UP",
    "code": 200,
    "error": null,
    "rtt": 251,
    "checkedAt": "2025-12-07T06:53:21.181Z"
  },
  {
    "name": "Monkeys Production",
    "url": "https://monkeys.support/healthz",
    "owner": "prnvtripathi",
    "status": "UP",
    "code": 200,
    "error": null,
    "rtt": 1071,
    "checkedAt": "2025-12-07T06:53:22.260Z"
  },
  {
    "name": "Monkeys Development",
    "url": "https://dev.monkeys.support/healthz",
    "owner": "prnvtripathi",
    "status": "UP",
    "code": 200,
    "error": null,
    "rtt": 1100,
    "checkedAt": "2025-12-07T06:53:23.362Z"
  },
  {
    "name": "Obligence",
    "url": "https://obligence.kyrexi.tech",
    "owner": "prnvtripathi",
    "status": "UP",
    "code": 200,
    "error": null,
    "rtt": 1359,
    "checkedAt": "2025-12-07T06:53:24.723Z"
  }
]