[
  {
    "name": "Trafyx",
    "url": "https://trafyx.kyrexi.tech",
    "owner": "prnvtripathi",
    "status": "DOWN",
    "code": 0,
    "error": "fetch failed",
    "rtt": 0,
    "checkedAt": "2026-04-11T06:06:07.785Z"
  },
  {
    "name": "Monkeys Production",
    "url": "https://monkeys.support/healthz",
    "owner": "prnvtripathi",
    "status": "UP",
    "code": 200,
    "error": null,
    "rtt": 1093,
    "checkedAt": "2026-04-11T06:06:09.090Z"
  },
  {
    "name": "Monkeys Development",
    "url": "https://dev.monkeys.support/healthz",
    "owner": "prnvtripathi",
    "status": "DOWN",
    "code": 0,
    "error": "This operation was aborted",
    "rtt": 0,
    "checkedAt": "2026-04-11T06:06:17.092Z"
  },
  {
    "name": "Obligence",
    "url": "https://obligence.kyrexi.tech",
    "owner": "prnvtripathi",
    "status": "DOWN",
    "code": 0,
    "error": "fetch failed",
    "rtt": 0,
    "checkedAt": "2026-04-11T06:06:17.555Z"
  }
]