[
  {
    "name": "Trafyx",
    "url": "https://trafyx.kyrexi.tech",
    "owner": "prnvtripathi",
    "status": "DOWN",
    "code": 0,
    "error": "fetch failed",
    "rtt": 0,
    "checkedAt": "2026-02-01T19:39:44.671Z"
  },
  {
    "name": "Monkeys Production",
    "url": "https://monkeys.support/healthz",
    "owner": "prnvtripathi",
    "status": "DOWN",
    "code": 0,
    "error": "This operation was aborted",
    "rtt": 0,
    "checkedAt": "2026-02-01T19:39:53.127Z"
  },
  {
    "name": "Monkeys Development",
    "url": "https://dev.monkeys.support/healthz",
    "owner": "prnvtripathi",
    "status": "DOWN",
    "code": 0,
    "error": "This operation was aborted",
    "rtt": 0,
    "checkedAt": "2026-02-01T19:40:01.531Z"
  },
  {
    "name": "Obligence",
    "url": "https://obligence.kyrexi.tech",
    "owner": "prnvtripathi",
    "status": "DOWN",
    "code": 0,
    "error": "fetch failed",
    "rtt": 0,
    "checkedAt": "2026-02-01T19:40:02.100Z"
  }
]